<?xml version="1.0" encoding="UTF-8"?><FORM><SUMMARY TITLE="BIC And IBAN Summary" POSITION="TEMPLATE" TMP_SCR_TYPE="M" CRITERIA_SRCH="N"><TYPE>S</TYPE><SUMMARY_DATA_BLK>BLK_ISTBS_BICIBAN_DIRECTORY</SUMMARY_DATA_BLK><SUMMARY_BASE></SUMMARY_BASE><SUMBLOCK SCREEN="SUMMARY" TABPAGE="QUERY" TYPE="SE"><FIELD ID="1" TYPE="ME"><NAME>RECORDKEY</NAME><TYPE>TEXT</TYPE><LBL>Record Key</LBL><REQD>-1</REQD><MAXLENGTH>8</MAXLENGTH><DTYPE>VARCHAR2</DTYPE><SIZE>8</SIZE></FIELD><FIELD ID="2" TYPE="ME"><NAME>BICCODE</NAME><TYPE>TEXT</TYPE><LBL>BIC Code</LBL><MAXLENGTH>8</MAXLENGTH><DTYPE>VARCHAR2</DTYPE><SIZE>8</SIZE></FIELD><FIELD ID="3" TYPE="ME"><NAME>IBANBICCODE</NAME><TYPE>TEXT</TYPE><LBL>Unique BIC Code</LBL><MAXLENGTH>8</MAXLENGTH><DTYPE>VARCHAR2</DTYPE><SIZE>8</SIZE></FIELD><FIELD ID="4" TYPE="ME"><NAME>ROUTINGBICCODE</NAME><TYPE>TEXT</TYPE><LBL>Routing BIC Code</LBL><MAXLENGTH>8</MAXLENGTH><DTYPE>VARCHAR2</DTYPE><SIZE>8</SIZE></FIELD><FIELD ID="5" TYPE="ME"><NAME>INSTITUTIONNAME</NAME><TYPE>TEXT</TYPE><LBL>Institution Name</LBL><MAXLENGTH>105</MAXLENGTH><DTYPE>VARCHAR2</DTYPE><SIZE>25</SIZE></FIELD><FIELD ID="6" TYPE="ME"><NAME>BRANCHCODE</NAME><TYPE>TEXT</TYPE><LBL>Branch Code</LBL><MAXLENGTH>3</MAXLENGTH><DTYPE>VARCHAR2</DTYPE><SIZE>3</SIZE></FIELD><FIELD ID="7" TYPE="ME"><NAME>IBANBRANCHCODE</NAME><TYPE>TEXT</TYPE><LBL>IBAN Branch Code</LBL><MAXLENGTH>3</MAXLENGTH><DTYPE>VARCHAR2</DTYPE><SIZE>3</SIZE></FIELD><FIELD ID="8" TYPE="ME"><NAME>ROUTINGBRANCHCODE</NAME><TYPE>TEXT</TYPE><LBL>Routing Branch Code</LBL><MAXLENGTH>3</MAXLENGTH><DTYPE>VARCHAR2</DTYPE><SIZE>3</SIZE></FIELD></SUMBLOCK><SUMBLOCK SCREEN="SUMMARY" TABPAGE="RESULT" TYPE="ME"><FIELD ID="1" TYPE="ME"><NAME>RECORDKEY</NAME><TYPE>TEXT</TYPE><LBL>Record Key</LBL><REQD>-1</REQD><MAXLENGTH>8</MAXLENGTH><DTYPE>VARCHAR2</DTYPE><SIZE>8</SIZE></FIELD><FIELD ID="2" TYPE="ME"><NAME>BICCODE</NAME><TYPE>TEXT</TYPE><LBL>BIC Code</LBL><MAXLENGTH>8</MAXLENGTH><DTYPE>VARCHAR2</DTYPE><SIZE>8</SIZE></FIELD><FIELD ID="3" TYPE="ME"><NAME>IBANBICCODE</NAME><TYPE>TEXT</TYPE><LBL>Unique BIC Code</LBL><MAXLENGTH>8</MAXLENGTH><DTYPE>VARCHAR2</DTYPE><SIZE>8</SIZE></FIELD><FIELD ID="4" TYPE="ME"><NAME>ROUTINGBICCODE</NAME><TYPE>TEXT</TYPE><LBL>Routing BIC Code</LBL><MAXLENGTH>8</MAXLENGTH><DTYPE>VARCHAR2</DTYPE><SIZE>8</SIZE></FIELD><FIELD ID="5" TYPE="ME"><NAME>INSTITUTIONNAME</NAME><TYPE>TEXT</TYPE><LBL>Institution Name</LBL><MAXLENGTH>105</MAXLENGTH><DTYPE>VARCHAR2</DTYPE><SIZE>25</SIZE></FIELD><FIELD ID="6" TYPE="ME"><NAME>BRANCHCODE</NAME><TYPE>TEXT</TYPE><LBL>Branch Code</LBL><MAXLENGTH>3</MAXLENGTH><DTYPE>VARCHAR2</DTYPE><SIZE>3</SIZE></FIELD><FIELD ID="7" TYPE="ME"><NAME>IBANBRANCHCODE</NAME><TYPE>TEXT</TYPE><LBL>IBAN Branch Code</LBL><MAXLENGTH>3</MAXLENGTH><DTYPE>VARCHAR2</DTYPE><SIZE>3</SIZE></FIELD><FIELD ID="8" TYPE="ME"><NAME>ROUTINGBRANCHCODE</NAME><TYPE>TEXT</TYPE><LBL>Routing Branch Code</LBL><MAXLENGTH>3</MAXLENGTH><DTYPE>VARCHAR2</DTYPE><SIZE>3</SIZE></FIELD></SUMBLOCK></SUMMARY><SCREEN NAME="CVS_MAIN" MAIN_WIN="Y" TITLE="BIC And IBAN Maintenance" POSITION="template" TMP_SCR_TYPE="L"><EXIT_BTN>1</EXIT_BTN><HEADER><TAB ID="TAB_HEADER"><LBL></LBL></TAB></HEADER><BODY><TAB ID="TAB_MAIN"><LBL></LBL><SECTION ID="SEC_S1" COLLAPSE="N"><LBL></LBL><PART ID="S1P1" NAME="S1P1" WIDTH="50"><FLDSET ID="FST_FS1" VIEW="SE" TYPE="SE" INDEX="1"><LBL>Unique Details</LBL><BLOCK>BLK_ISTBS_BICIBAN_DIRECTORY</BLOCK><HREQ>0</HREQ><HEIGHT></HEIGHT><WIDTH></WIDTH><FIELD INDEX="" CONTROL="N" SPRT="1"><NAME>RECORDKEY</NAME><TYPE>TEXT</TYPE><LBL>Record Key</LBL><REQD>-1</REQD><MAXLENGTH>8</MAXLENGTH><DTYPE>VARCHAR2</DTYPE><SIZE>8</SIZE><ROWS></ROWS><COLS></COLS></FIELD><FIELD INDEX="" CONTROL="N" SPRT="1"><NAME>INSTITUTIONNAME</NAME><TYPE>TEXT</TYPE><LBL>Institution Name</LBL><MAXLENGTH>105</MAXLENGTH><DTYPE>VARCHAR2</DTYPE><SIZE>25</SIZE><ROWS></ROWS><COLS></COLS></FIELD><FIELD INDEX="" CONTROL="N" SPRT="1"><NAME>BICCODE</NAME><TYPE>TEXT</TYPE><LBL>BIC Code</LBL><MAXLENGTH>8</MAXLENGTH><DTYPE>VARCHAR2</DTYPE><SIZE>8</SIZE><ROWS></ROWS><COLS></COLS></FIELD><FIELD INDEX="" CONTROL="N" SPRT="1"><NAME>BRANCHCODE</NAME><TYPE>TEXT</TYPE><LBL>Branch Code</LBL><MAXLENGTH>3</MAXLENGTH><DTYPE>VARCHAR2</DTYPE><SIZE>3</SIZE><ROWS></ROWS><COLS></COLS></FIELD></FLDSET></PART><PART ID="S1P2" NAME="S1P2" WIDTH="50"><FLDSET ID="FST_FS2" VIEW="SE" TYPE="SE" INDEX="1"><LBL>IBAN Details</LBL><BLOCK>BLK_ISTBS_BICIBAN_DIRECTORY</BLOCK><HREQ>0</HREQ><HEIGHT></HEIGHT><WIDTH></WIDTH><FIELD INDEX="" CONTROL="N"><NAME>UNIQUEBICCODE</NAME><TYPE>TEXT</TYPE><LBL>Unique BIC Code</LBL><MAXLENGTH>8</MAXLENGTH><DTYPE>VARCHAR2</DTYPE><SIZE>8</SIZE><ROWS></ROWS><COLS></COLS></FIELD><FIELD INDEX="" CONTROL="N"><NAME>IBANBRANCHCODE</NAME><TYPE>TEXT</TYPE><LBL>IBAN Branch Code</LBL><MAXLENGTH>3</MAXLENGTH><DTYPE>VARCHAR2</DTYPE><SIZE>3</SIZE><ROWS></ROWS><COLS></COLS></FIELD><FIELD INDEX="" CONTROL="N"><NAME>ROUTINGBICCODE</NAME><TYPE>TEXT</TYPE><LBL>Routing BIC Code</LBL><MAXLENGTH>8</MAXLENGTH><DTYPE>VARCHAR2</DTYPE><SIZE>8</SIZE><ROWS></ROWS><COLS></COLS></FIELD><FIELD INDEX="" CONTROL="N"><NAME>ROUTINGBRANCHCODE</NAME><TYPE>TEXT</TYPE><LBL>Routing Branch Code</LBL><MAXLENGTH>3</MAXLENGTH><DTYPE>VARCHAR2</DTYPE><SIZE>3</SIZE><ROWS></ROWS><COLS></COLS></FIELD></FLDSET></PART></SECTION><SECTION ID="SEC_S2" COLLAPSE="N"><LBL></LBL><PART ID="S2P1" NAME="S2P1" WIDTH="50"><SPRTCNT>2</SPRTCNT><FLDSET ID="FST_FS3" VIEW="SE" TYPE="SE" INDEX="1"><LBL>Country Details</LBL><BLOCK>BLK_ISTBS_BICIBAN_DIRECTORY</BLOCK><HREQ>0</HREQ><HEIGHT></HEIGHT><WIDTH></WIDTH><FIELD INDEX="" CONTROL="N" SPRT="1"><NAME>IBANBICCODE</NAME><TYPE>TEXT</TYPE><LBL>Unique BIC Code</LBL><MAXLENGTH>8</MAXLENGTH><DTYPE>VARCHAR2</DTYPE><SIZE>8</SIZE><ROWS></ROWS><COLS></COLS></FIELD><FIELD INDEX="" CONTROL="N" SPRT="1"><NAME>UNIQUEBRANCHCODE</NAME><TYPE>TEXT</TYPE><LBL>Unique Branch Code</LBL><MAXLENGTH>3</MAXLENGTH><DTYPE>VARCHAR2</DTYPE><SIZE>3</SIZE><ROWS></ROWS><COLS></COLS></FIELD><FIELD INDEX="" CONTROL="N" SPRT="1"><NAME>COUNTRYCODE</NAME><TYPE>TEXT</TYPE><LBL>Country</LBL><MAXLENGTH>2</MAXLENGTH><DTYPE>VARCHAR2</DTYPE><SIZE>2</SIZE><ROWS></ROWS><COLS></COLS></FIELD><FIELD INDEX="" CONTROL="N" SPRT="1"><NAME>NATIONALID</NAME><TYPE>TEXT</TYPE><LBL>National ID</LBL><MAXLENGTH>15</MAXLENGTH><DTYPE>VARCHAR2</DTYPE><SIZE>15</SIZE><ROWS></ROWS><COLS></COLS></FIELD><FIELD INDEX="" CONTROL="N" SPRT="1"><NAME>LOCATION</NAME><TYPE>TEXT</TYPE><LBL>Location</LBL><MAXLENGTH>90</MAXLENGTH><DTYPE>VARCHAR2</DTYPE><SIZE>25</SIZE><ROWS></ROWS><COLS></COLS></FIELD><FIELD INDEX="" CONTROL="N" SPRT="1"><NAME>COUNTRYNAME</NAME><TYPE>TEXT</TYPE><LBL>Country Name</LBL><MAXLENGTH>70</MAXLENGTH><DTYPE>VARCHAR2</DTYPE><SIZE>25</SIZE><ROWS></ROWS><COLS></COLS></FIELD></FLDSET><FLDSET ID="FST_FS5" VIEW="SE" TYPE="SE" INDEX="2"><LBL></LBL><BLOCK>BLK_ISTBS_BICIBAN_DIRECTORY</BLOCK><HREQ>0</HREQ><HEIGHT></HEIGHT><WIDTH></WIDTH><FIELD INDEX="" CONTROL="N" SPRT="2"><NAME>IBANCOUNTRYCODE</NAME><TYPE>TEXT</TYPE><LBL>IBAN Country Code</LBL><MAXLENGTH>2</MAXLENGTH><DTYPE>VARCHAR2</DTYPE><SIZE>2</SIZE><ROWS></ROWS><COLS></COLS></FIELD><FIELD INDEX="" CONTROL="N" SPRT="2"><NAME>IBANNATIONALID</NAME><TYPE>TEXT</TYPE><LBL>IBAN National ID</LBL><MAXLENGTH>15</MAXLENGTH><DTYPE>VARCHAR2</DTYPE><SIZE>15</SIZE><ROWS></ROWS><COLS></COLS></FIELD><FIELD INDEX="" CONTROL="N" SPRT="2"><NAME>UNIQUEIBANNATIONALID</NAME><TYPE>TEXT</TYPE><LBL>Unique IBAN National ID</LBL><MAXLENGTH>15</MAXLENGTH><DTYPE>VARCHAR2</DTYPE><SIZE>15</SIZE><ROWS></ROWS><COLS></COLS></FIELD><FIELD INDEX="" CONTROL="N" SPRT="2"><NAME>SUBTYPEINDICATOR</NAME><TYPE>TEXT</TYPE><LBL>Subtype Indicator</LBL><MAXLENGTH>4</MAXLENGTH><DTYPE>VARCHAR2</DTYPE><SIZE>4</SIZE><ROWS></ROWS><COLS></COLS></FIELD><FIELD INDEX="" CONTROL="N" SPRT="2"><NAME>SERVICECODES</NAME><TYPE>TEXT</TYPE><LBL>Service Codes</LBL><MAXLENGTH>60</MAXLENGTH><DTYPE>VARCHAR2</DTYPE><SIZE>25</SIZE><ROWS></ROWS><COLS></COLS></FIELD><FIELD INDEX="" CONTROL="N" SPRT="2"><NAME>NATIONALIDEXPIRYDATE</NAME><TYPE>DATE</TYPE><LBL>National ID Expiry Date</LBL><MAXLENGTH>11</MAXLENGTH><DTYPE>DATE</DTYPE><SIZE>10</SIZE><ROWS></ROWS><COLS></COLS></FIELD></FLDSET></PART><PART ID="S2P2" NAME="S2P2" WIDTH="50"><SPRTCNT>2</SPRTCNT><FLDSET ID="FST_FS4" VIEW="SE" TYPE="SE" INDEX="1"><LBL></LBL><BLOCK>BLK_ISTBS_BICIBAN_DIRECTORY</BLOCK><HREQ>0</HREQ><HEIGHT></HEIGHT><WIDTH></WIDTH><FIELD INDEX="" CONTROL="N" SPRT="1"><NAME>CITYHEADING</NAME><TYPE>TEXT</TYPE><LBL>City Heading</LBL><MAXLENGTH>35</MAXLENGTH><DTYPE>VARCHAR2</DTYPE><SIZE>25</SIZE><ROWS></ROWS><COLS></COLS></FIELD><FIELD INDEX="" CONTROL="N" SPRT="1"><NAME>BRANCHINFORMATION</NAME><TYPE>TEXT</TYPE><LBL>Branch Info</LBL><MAXLENGTH>70</MAXLENGTH><DTYPE>VARCHAR2</DTYPE><SIZE>25</SIZE><ROWS></ROWS><COLS></COLS></FIELD><FIELD INDEX="" CONTROL="N" SPRT="1"><NAME>PARENTBANKCODE</NAME><TYPE>TEXT</TYPE><LBL>Parent Bank Code</LBL><MAXLENGTH>4</MAXLENGTH><DTYPE>VARCHAR2</DTYPE><SIZE>4</SIZE><ROWS></ROWS><COLS></COLS></FIELD><FIELD INDEX="" CONTROL="N" SPRT="1"><NAME>UNIQUENATIONALID</NAME><TYPE>TEXT</TYPE><LBL>Unique National ID</LBL><MAXLENGTH>15</MAXLENGTH><DTYPE>VARCHAR2</DTYPE><SIZE>15</SIZE><ROWS></ROWS><COLS></COLS></FIELD><FIELD INDEX="" CONTROL="N" SPRT="1"><NAME>CHIPSUID</NAME><TYPE>TEXT</TYPE><MAX_DECIMALS></MAX_DECIMALS><LBL>Chips ID</LBL><MAXLENGTH>6</MAXLENGTH><DTYPE>NUMBER</DTYPE><MAX_VAL></MAX_VAL><MIN_VAL></MIN_VAL><SIZE>6</SIZE><ROWS></ROWS><COLS></COLS></FIELD><FIELD INDEX="" CONTROL="N" SPRT="1"><NAME>BRANCHQUALIFIER</NAME><TYPE>TEXT</TYPE><LBL>Branch Qualifier</LBL><MAXLENGTH>35</MAXLENGTH><DTYPE>VARCHAR2</DTYPE><SIZE>25</SIZE><ROWS></ROWS><COLS></COLS></FIELD><FIELD INDEX="" CONTROL="N" SPRT="1"><NAME>SPECIALCODE</NAME><TYPE>TEXT</TYPE><LBL>Special Code</LBL><MAXLENGTH>6</MAXLENGTH><DTYPE>VARCHAR2</DTYPE><SIZE>6</SIZE><ROWS></ROWS><COLS></COLS></FIELD></FLDSET><FLDSET ID="FST_FS6" VIEW="SE" TYPE="SE" INDEX="2"><LBL></LBL><BLOCK>BLK_ISTBS_BICIBAN_DIRECTORY</BLOCK><HREQ>0</HREQ><HEIGHT></HEIGHT><WIDTH></WIDTH><FIELD INDEX="" CONTROL="N" SPRT="2"><NAME>OTHERNATIONALID1</NAME><TYPE>TEXT</TYPE><LBL>Other National ID1</LBL><MAXLENGTH>17</MAXLENGTH><DTYPE>VARCHAR2</DTYPE><SIZE>17</SIZE><ROWS></ROWS><COLS></COLS></FIELD><FIELD INDEX="" CONTROL="N" SPRT="2"><NAME>OTHER_NATIONALID2</NAME><TYPE>TEXT</TYPE><LBL>Other National ID2</LBL><MAXLENGTH>17</MAXLENGTH><DTYPE>VARCHAR2</DTYPE><SIZE>17</SIZE><ROWS></ROWS><COLS></COLS></FIELD><FIELD INDEX="" CONTROL="N" SPRT="2"><NAME>ZIPCODE</NAME><TYPE>TEXT</TYPE><LBL>ZIP Code</LBL><MAXLENGTH>15</MAXLENGTH><DTYPE>VARCHAR2</DTYPE><SIZE>15</SIZE><ROWS></ROWS><COLS></COLS></FIELD><FIELD INDEX="" CONTROL="N" SPRT="2"><NAME>POBNUMBER</NAME><TYPE>TEXT</TYPE><LBL>POB Number</LBL><MAXLENGTH>35</MAXLENGTH><DTYPE>VARCHAR2</DTYPE><SIZE>25</SIZE><ROWS></ROWS><COLS></COLS></FIELD><FIELD INDEX="" CONTROL="N" SPRT="2"><NAME>POBZIPCODE</NAME><TYPE>TEXT</TYPE><LBL>POB ZIP Code</LBL><MAXLENGTH>15</MAXLENGTH><DTYPE>VARCHAR2</DTYPE><SIZE>15</SIZE><ROWS></ROWS><COLS></COLS></FIELD><FIELD INDEX="" CONTROL="N" SPRT="2"><NAME>POBLOCATION</NAME><TYPE>TEXT</TYPE><LBL>POB Location</LBL><MAXLENGTH>90</MAXLENGTH><DTYPE>VARCHAR2</DTYPE><SIZE>25</SIZE><ROWS></ROWS><COLS></COLS></FIELD><FIELD INDEX="" CONTROL="N" SPRT="2"><NAME>POBCOUNTRYNAME</NAME><TYPE>TEXT</TYPE><LBL>POB Country Name</LBL><MAXLENGTH>70</MAXLENGTH><DTYPE>VARCHAR2</DTYPE><SIZE>25</SIZE><ROWS></ROWS><COLS></COLS></FIELD></FLDSET></PART></SECTION><SECTION ID="SEC_S3" COLLAPSE="N"><LBL></LBL><PART ID="S3P1" NAME="S3P1" WIDTH="100"><FLDSET ID="FST_FS7" VIEW="SE" TYPE="SE" INDEX="1"><LBL>Address</LBL><BLOCK>BLK_ISTBS_BICIBAN_DIRECTORY</BLOCK><HREQ>0</HREQ><HEIGHT></HEIGHT><WIDTH></WIDTH><FIELD INDEX="" CONTROL="N"><NAME>PHYSICALADDRESS1</NAME><TYPE>TEXT</TYPE><LBL>Physical Address1</LBL><MAXLENGTH>35</MAXLENGTH><DTYPE>VARCHAR2</DTYPE><SIZE>35</SIZE><ROWS></ROWS><COLS></COLS></FIELD><FIELD INDEX="" CONTROL="N"><NAME>PHYSICALADDRESS2</NAME><TYPE>TEXT</TYPE><LBL>Physical Address2</LBL><MAXLENGTH>35</MAXLENGTH><DTYPE>VARCHAR2</DTYPE><SIZE>35</SIZE><ROWS></ROWS><COLS></COLS></FIELD><FIELD INDEX="" CONTROL="N"><NAME>PHYSICALADDRESS3</NAME><TYPE>TEXT</TYPE><LBL>Physical Address3</LBL><MAXLENGTH>35</MAXLENGTH><DTYPE>VARCHAR2</DTYPE><SIZE>35</SIZE><ROWS></ROWS><COLS></COLS></FIELD><FIELD INDEX="" CONTROL="N"><NAME>PHYSICALADDRESS4</NAME><TYPE>TEXT</TYPE><LBL>Physical Address4</LBL><MAXLENGTH>35</MAXLENGTH><DTYPE>VARCHAR2</DTYPE><SIZE>35</SIZE><ROWS></ROWS><COLS></COLS></FIELD></FLDSET></PART></SECTION></TAB></BODY><FOOTER><TAB ID="TAB_FOOTER"><LBL></LBL></TAB></FOOTER><SUBSCREEN><FORM SEQ="1" TYPE="VL" id=""><FUNCTION></FUNCTION><SCREEN></SCREEN><LBL>Change Log</LBL></FORM></SUBSCREEN></SCREEN></FORM>